CS6102_assignment-1/part1/multiplier.v
module multiplier(input wire [3:0] a, b, output wire [3:0] out) ;
    wire p0, p1, p2, p3, p4, p5, p6;

    assign p0 = (a[0] & b[0]);
    assign p1 = (a[1] & b[0]) ^ (a[0] & b[1]);
    assign p2 = (a[2] & b[0]) ^ (a[1] & b[1]) ^ (a[0] & b[2]);
    assign p3 = (a[3] & b[0]) ^ (a[2] & b[1]) ^ (a[1] & b[2]) ^ (a[0] & b[3]);
    assign p4 = (a[3] & b[1]) ^ (a[2] & b[2]) ^ (a[1] & b[3]);
    assign p5 = (a[3] & b[2]) ^ (a[2] & b[3]);
    assign p6 = (a[3] & b[3]);

    assign out[0] = p0 ^ p4;
    assign out[1] = p1 ^ p4 ^ p5;
    assign out[2] = p2 ^ p5 ^ p6;
    assign out[3] = p3 ^ p6;

endmodule

CS6102_assignment-1/part1/multiplier_tb.v
`timescale 1ns / 1ps

module multiplier_tb;

    reg  [3:0] a;
    reg  [3:0] b;
    wire [3:0] out;
    
    integer i, j;

    multiplier uut (.a(a), .b(b), .out(out));

    initial begin
        $display("Starting GF(2^4) Multiplier Test...");
        $display("------------------------------------");
        $display("  A  |  B  | Result (OUT)");
        $display("------------------------------------");

        for (i = 0; i < 16; i = i + 1) begin
            for (j = 0; j < 16; j = j + 1) begin
                
                a = i; 
                b = j;
                
                #10;
                
                $display(" %h  |  %h  |   %h", a, b, out);
            end
        end

        $display("------------------------------------");
        $display("Simulation Finished.");
        $finish;
    end

    initial begin
        $dumpfile("multiplier.vcd");
        $dumpvars(0, multiplier_tb);
    end

endmodule

CS6102_assignment-1/part1/multiplier.vcd
$date
	Tue Feb 17 21:23:59 2026
$end
$version
	Icarus Verilog
$end
$timescale
	1ps
$end
$scope module multiplier_tb $end
$var wire 4 ! out [3:0] $end
$var reg 4 " a [3:0] $end
$var reg 4 # b [3:0] $end
$var integer 32 $ i [31:0] $end
$var integer 32 % j [31:0] $end
$scope module uut $end
$var wire 4 & a [3:0] $end
$var wire 4 ' b [3:0] $end
$var wire 1 ( p0 $end
$var wire 1 ) p1 $end
$var wire 1 * p2 $end
$var wire 1 + p3 $end
$var wire 1 , p4 $end
$var wire 1 - p5 $end
$var wire 1 . p6 $end
$var wire 4 / out [3:0] $end
$upscope $end
$upscope $end
$enddefinitions $end
$comment Show the parameter values. $end
$dumpall
$end
#0
$dumpvars
b0 /
0.
0-
0,
0+
0*
0)
0(
b0 '
b0 &
b0 %
b0 $
b0 #
b0 "
b0 !
$end
#10000
b1 #
b1 '
b1 %
#20000
b10 #
b10 '
b10 %
#30000
b11 #
b11 '
b11 %
#40000
b100 #
b100 '
b100 %
#50000
b101 #
b101 '
b101 %
#60000
b110 #
b110 '
b110 %
#70000
b111 #
b111 '
b111 %
#80000
b1000 #
b1000 '
b1000 %
#90000
b1001 #
b1001 '
b1001 %
#100000
b1010 #
b1010 '
b1010 %
#110000
b1011 #
b1011 '
b1011 %
#120000
b1100 #
b1100 '
b1100 %
#130000
b1101 #
b1101 '
b1101 %
#140000
b1110 #
b1110 '
b1110 %
#150000
b1111 #
b1111 '
b1111 %
#160000
b0 #
b0 '
b1 "
b1 &
b1 $
b0 %
#170000
b1 !
b1 /
1(
b1 #
b1 '
b1 %
#180000
b10 !
b10 /
1)
0(
b10 #
b10 '
b10 %
#190000
b11 !
b11 /
1(
b11 #
b11 '
b11 %
#200000
b100 !
b100 /
0)
1*
0(
b100 #
b100 '
b100 %
#210000
b101 !
b101 /
1(
b101 #
b101 '
b101 %
#220000
b110 !
b110 /
1)
0(
b110 #
b110 '
b110 %
#230000
b111 !
b111 /
1(
b111 #
b111 '
b111 %
#240000
b1000 !
b1000 /
0)
0*
1+
0(
b1000 #
b1000 '
b1000 %
#250000
b1001 !
b1001 /
1(
b1001 #
b1001 '
b1001 %
#260000
b1010 !
b1010 /
1)
0(
b1010 #
b1010 '
b1010 %
#270000
b1011 !
b1011 /
1(
b1011 #
b1011 '
b1011 %
#280000
b1100 !
b1100 /
0)
1*
0(
b1100 #
b1100 '
b1100 %
#290000
b1101 !
b1101 /
1(
b1101 #
b1101 '
b1101 %
#300000
b1110 !
b1110 /
1)
0(
b1110 #
b1110 '
b1110 %
#310000
b1111 !
b1111 /
1(
b1111 #
b1111 '
b1111 %
#320000
b0 !
b0 /
0)
0*
0+
0(
b0 #
b0 '
b10 "
b10 &
b10 $
b0 %
#330000
b10 !
b10 /
1)
b1 #
b1 '
b1 %
#340000
b100 !
b100 /
1*
0)
b10 #
b10 '
b10 %
#350000
b110 !
b110 /
1)
b11 #
b11 '
b11 %
#360000
b1000 !
b1000 /
0*
1+
0)
b100 #
b100 '
b100 %
#370000
b1010 !
b1010 /
1)
b101 #
b101 '
b101 %
#380000
b1100 !
b1100 /
1*
0)
b110 #
b110 '
b110 %
#390000
b1110 !
b1110 /
1)
b111 #
b111 '
b111 %
#400000
0*
0+
b11 !
b11 /
0)
1,
b1000 #
b1000 '
b1000 %
#410000
b1 !
b1 /
1)
b1001 #
b1001 '
b1001 %
#420000
b111 !
b111 /
1*
0)
b1010 #
b1010 '
b1010 %
#430000
b101 !
b101 /
1)
b1011 #
b1011 '
b1011 %
#440000
b1011 !
b1011 /
0*
1+
0)
b1100 #
b1100 '
b1100 %
#450000
b1001 !
b1001 /
1)
b1101 #
b1101 '
b1101 %
#460000
b1111 !
b1111 /
1*
0)
b1110 #
b1110 '
b1110 %
#470000
b1101 !
b1101 /
1)
b1111 #
b1111 '
b1111 %
#480000
0*
0+
b0 !
b0 /
0)
0,
b0 #
b0 '
b11 "
b11 &
b11 $
b0 %
#490000
b11 !
b11 /
1)
1(
b1 #
b1 '
b1 %
#500000
1*
b110 !
b110 /
0(
b10 #
b10 '
b10 %
#510000
b101 !
b101 /
0)
1(
b11 #
b11 '
b11 %
#520000
1+
b1100 !
b1100 /
1*
0(
b100 #
b100 '
b100 %
#530000
b1111 !
b1111 /
1)
1(
b101 #
b101 '
b101 %
#540000
0*
b1010 !
b1010 /
0(
b110 #
b110 '
b110 %
#550000
b1001 !
b1001 /
0)
1(
b111 #
b111 '
b111 %
#560000
b1011 !
b1011 /
0*
1+
1,
0(
b1000 #
b1000 '
b1000 %
#570000
b1000 !
b1000 /
1)
1(
b1001 #
b1001 '
b1001 %
#580000
1*
b1101 !
b1101 /
0(
b1010 #
b1010 '
b1010 %
#590000
b1110 !
b1110 /
0)
1(
b1011 #
b1011 '
b1011 %
#600000
0+
b111 !
b111 /
1*
0(
b1100 #
b1100 '
b1100 %
#610000
b100 !
b100 /
1)
1(
b1101 #
b1101 '
b1101 %
#620000
0*
b1 !
b1 /
0(
b1110 #
b1110 '
b1110 %
#630000
b10 !
b10 /
0)
1(
b1111 #
b1111 '
b1111 %
#640000
b0 !
b0 /
0*
0+
0,
0(
b0 #
b0 '
b100 "
b100 &
b100 $
b0 %
#650000
b100 !
b100 /
1*
b1 #
b1 '
b1 %
#660000
b1000 !
b1000 /
1+
0*
b10 #
b10 '
b10 %
#670000
b1100 !
b1100 /
1*
b11 #
b11 '
b11 %
#680000
0+
b11 !
b11 /
0*
1,
b100 #
b100 '
b100 %
#690000
b111 !
b111 /
1*
b101 #
b101 '
b101 %
#700000
b1011 !
b1011 /
1+
0*
b110 #
b110 '
b110 %
#710000
b1111 !
b1111 /
1*
b111 #
b111 '
b111 %
#720000
0+
0*
0,
b110 !
b110 /
1-
b1000 #
b1000 '
b1000 %
#730000
b10 !
b10 /
1*
b1001 #
b1001 '
b1001 %
#740000
b1110 !
b1110 /
1+
0*
b1010 #
b1010 '
b1010 %
#750000
b1010 !
b1010 /
1*
b1011 #
b1011 '
b1011 %
#760000
0+
b101 !
b101 /
0*
1,
b1100 #
b1100 '
b1100 %
#770000
b1 !
b1 /
1*
b1101 #
b1101 '
b1101 %
#780000
b1101 !
b1101 /
1+
0*
b1110 #
b1110 '
b1110 %
#790000
b1001 !
b1001 /
1*
b1111 #
b1111 '
b1111 %
#800000
0+
0*
0,
b0 !
b0 /
0-
b0 #
b0 '
b101 "
b101 &
b101 $
b0 %
#810000
1*
b101 !
b101 /
1(
b1 #
b1 '
b1 %
#820000
1+
0*
b1010 !
b1010 /
1)
0(
b10 #
b10 '
b10 %
#830000
1*
b1111 !
b1111 /
1(
b11 #
b11 '
b11 %
#840000
0+
1,
b111 !
b111 /
0)
1*
0(
b100 #
b100 '
b100 %
#850000
0*
b10 !
b10 /
1(
b101 #
b101 '
b101 %
#860000
1+
1*
b1101 !
b1101 /
1)
0(
b110 #
b110 '
b110 %
#870000
0*
b1000 !
b1000 /
1(
b111 #
b111 '
b111 %
#880000
0,
b1110 !
b1110 /
0)
0*
1+
1-
0(
b1000 #
b1000 '
b1000 %
#890000
1*
b1011 !
b1011 /
1(
b1001 #
b1001 '
b1001 %
#900000
0+
0*
b100 !
b100 /
1)
0(
b1010 #
b1010 '
b1010 %
#910000
1*
b1 !
b1 /
1(
b1011 #
b1011 '
b1011 %
#920000
1+
1,
b1001 !
b1001 /
0)
1*
0(
b1100 #
b1100 '
b1100 %
#930000
0*
b1100 !
b1100 /
1(
b1101 #
b1101 '
b1101 %
#940000
0+
1*
b11 !
b11 /
1)
0(
b1110 #
b1110 '
b1110 %
#950000
0*
b110 !
b110 /
1(
b1111 #
b1111 '
b1111 %
#960000
0,
0-
b0 !
b0 /
0)
0*
0+
0(
b0 #
b0 '
b110 "
b110 &
b110 $
b0 %
#970000
b110 !
b110 /
1*
1)
b1 #
b1 '
b1 %
#980000
b1100 !
b1100 /
1+
0)
b10 #
b10 '
b10 %
#990000
b1010 !
b1010 /
0*
1)
b11 #
b11 '
b11 %
#1000000
b1011 !
b1011 /
1+
1,
0)
b100 #
b100 '
b100 %
#1010000
b1101 !
b1101 /
1*
1)
b101 #
b101 '
b101 %
#1020000
b111 !
b111 /
0+
0)
b110 #
b110 '
b110 %
#1030000
b1 !
b1 /
0*
1)
b111 #
b111 '
b111 %
#1040000
0+
b101 !
b101 /
0)
1,
1-
b1000 #
b1000 '
b1000 %
#1050000
b11 !
b11 /
1*
1)
b1001 #
b1001 '
b1001 %
#1060000
b1001 !
b1001 /
1+
0)
b1010 #
b1010 '
b1010 %
#1070000
b1111 !
b1111 /
0*
1)
b1011 #
b1011 '
b1011 %
#1080000
b1110 !
b1110 /
1+
0,
0)
b1100 #
b1100 '
b1100 %
#1090000
b1000 !
b1000 /
1*
1)
b1101 #
b1101 '
b1101 %
#1100000
b10 !
b10 /
0+
0)
b1110 #
b1110 '
b1110 %
#1110000
b100 !
b100 /
0*
1)
b1111 #
b1111 '
b1111 %
#1120000
0+
b0 !
b0 /
0)
0,
0-
b0 #
b0 '
b111 "
b111 &
b111 $
b0 %
#1130000
1*
b111 !
b111 /
1)
1(
b1 #
b1 '
b1 %
#1140000
1+
b1110 !
b1110 /
0(
b10 #
b10 '
b10 %
#1150000
0*
b1001 !
b1001 /
0)
1(
b11 #
b11 '
b11 %
#1160000
1+
1,
b1111 !
b1111 /
1*
0(
b100 #
b100 '
b100 %
#1170000
0*
b1000 !
b1000 /
1)
1(
b101 #
b101 '
b101 %
#1180000
0+
b1 !
b1 /
0(
b110 #
b110 '
b110 %
#1190000
1*
b110 !
b110 /
0)
1(
b111 #
b111 '
b111 %
#1200000
b1101 !
b1101 /
0*
1+
1,
1-
0(
b1000 #
b1000 '
b1000 %
#1210000
1*
b1010 !
b1010 /
1)
1(
b1001 #
b1001 '
b1001 %
#1220000
0+
b11 !
b11 /
0(
b1010 #
b1010 '
b1010 %
#1230000
0*
b100 !
b100 /
0)
1(
b1011 #
b1011 '
b1011 %
#1240000
0+
0,
b10 !
b10 /
1*
0(
b1100 #
b1100 '
b1100 %
#1250000
0*
b101 !
b101 /
1)
1(
b1101 #
b1101 '
b1101 %
#1260000
1+
b1100 !
b1100 /
0(
b1110 #
b1110 '
b1110 %
#1270000
1*
b1011 !
b1011 /
0)
1(
b1111 #
b1111 '
b1111 %
#1280000
b0 !
b0 /
0*
0+
0,
0-
0(
b0 #
b0 '
b1000 "
b1000 &
b1000 $
b0 %
#1290000
b1000 !
b1000 /
1+
b1 #
b1 '
b1 %
#1300000
0+
b11 !
b11 /
1,
b10 #
b10 '
b10 %
#1310000
b1011 !
b1011 /
1+
b11 #
b11 '
b11 %
#1320000
0+
0,
b110 !
b110 /
1-
b100 #
b100 '
b100 %
#1330000
b1110 !
b1110 /
1+
b101 #
b101 '
b101 %
#1340000
0+
b101 !
b101 /
1,
b110 #
b110 '
b110 %
#1350000
b1101 !
b1101 /
1+
b111 #
b111 '
b111 %
#1360000
0+
0,
0-
b1100 !
b1100 /
1.
b1000 #
b1000 '
b1000 %
#1370000
b100 !
b100 /
1+
b1001 #
b1001 '
b1001 %
#1380000
0+
b1111 !
b1111 /
1,
b1010 #
b1010 '
b1010 %
#1390000
b111 !
b111 /
1+
b1011 #
b1011 '
b1011 %
#1400000
0+
0,
b1010 !
b1010 /
1-
b1100 #
b1100 '
b1100 %
#1410000
b10 !
b10 /
1+
b1101 #
b1101 '
b1101 %
#1420000
0+
b1001 !
b1001 /
1,
b1110 #
b1110 '
b1110 %
#1430000
b1 !
b1 /
1+
b1111 #
b1111 '
b1111 %
#1440000
0+
0,
0-
b0 !
b0 /
0.
b0 #
b0 '
b1001 "
b1001 &
b1001 $
b0 %
#1450000
1+
b1001 !
b1001 /
1(
b1 #
b1 '
b1 %
#1460000
0+
1,
b1 !
b1 /
1)
0(
b10 #
b10 '
b10 %
#1470000
1+
b1000 !
b1000 /
1(
b11 #
b11 '
b11 %
#1480000
0+
0,
b10 !
b10 /
0)
1*
1-
0(
b100 #
b100 '
b100 %
#1490000
1+
b1011 !
b1011 /
1(
b101 #
b101 '
b101 %
#1500000
0+
1,
b11 !
b11 /
1)
0(
b110 #
b110 '
b110 %
#1510000
1+
b1010 !
b1010 /
1(
b111 #
b111 '
b111 %
#1520000
0,
0)
0*
1+
0-
b100 !
b100 /
0(
1.
b1000 #
b1000 '
b1000 %
#1530000
0+
b1101 !
b1101 /
1(
b1001 #
b1001 '
b1001 %
#1540000
1+
1,
b101 !
b101 /
1)
0(
b1010 #
b1010 '
b1010 %
#1550000
0+
b1100 !
b1100 /
1(
b1011 #
b1011 '
b1011 %
#1560000
1+
0,
b110 !
b110 /
0)
1*
1-
0(
b1100 #
b1100 '
b1100 %
#1570000
0+
b1111 !
b1111 /
1(
b1101 #
b1101 '
b1101 %
#1580000
1+
1,
b111 !
b111 /
1)
0(
b1110 #
b1110 '
b1110 %
#1590000
0+
b1110 !
b1110 /
1(
b1111 #
b1111 '
b1111 %
#1600000
0,
0-
b0 !
b0 /
0)
0*
0+
0.
0(
b0 #
b0 '
b1010 "
b1010 &
b1010 $
b0 %
#1610000
b1010 !
b1010 /
1+
1)
b1 #
b1 '
b1 %
#1620000
0+
b111 !
b111 /
1*
1,
0)
b10 #
b10 '
b10 %
#1630000
b1101 !
b1101 /
1+
1)
b11 #
b11 '
b11 %
#1640000
0*
1+
0,
b1110 !
b1110 /
0)
1-
b100 #
b100 '
b100 %
#1650000
b100 !
b100 /
0+
1)
b101 #
b101 '
b101 %
#1660000
1+
b1001 !
b1001 /
1*
1,
0)
b110 #
b110 '
b110 %
#1670000
b11 !
b11 /
0+
1)
b111 #
b111 '
b111 %
#1680000
0*
0+
0)
1,
0-
b1111 !
b1111 /
1.
b1000 #
b1000 '
b1000 %
#1690000
b101 !
b101 /
1+
1)
b1001 #
b1001 '
b1001 %
#1700000
0+
b1000 !
b1000 /
1*
0,
0)
b1010 #
b1010 '
b1010 %
#1710000
b10 !
b10 /
1+
1)
b1011 #
b1011 '
b1011 %
#1720000
0*
1+
1,
b1 !
b1 /
0)
1-
b1100 #
b1100 '
b1100 %
#1730000
b1011 !
b1011 /
0+
1)
b1101 #
b1101 '
b1101 %
#1740000
1+
b110 !
b110 /
1*
0,
0)
b1110 #
b1110 '
b1110 %
#1750000
b1100 !
b1100 /
0+
1)
b1111 #
b1111 '
b1111 %
#1760000
0*
0+
0)
0,
0-
b0 !
b0 /
0.
b0 #
b0 '
b1011 "
b1011 &
b1011 $
b0 %
#1770000
1+
b1011 !
b1011 /
1)
1(
b1 #
b1 '
b1 %
#1780000
0+
1*
1,
b101 !
b101 /
0(
b10 #
b10 '
b10 %
#1790000
1+
b1110 !
b1110 /
0)
1(
b11 #
b11 '
b11 %
#1800000
1+
0,
b1010 !
b1010 /
1*
1-
0(
b100 #
b100 '
b100 %
#1810000
0+
b1 !
b1 /
1)
1(
b101 #
b101 '
b101 %
#1820000
1+
0*
1,
b1111 !
b1111 /
0(
b110 #
b110 '
b110 %
#1830000
0+
b100 !
b100 /
0)
1(
b111 #
b111 '
b111 %
#1840000
0*
1+
1,
0-
b111 !
b111 /
0(
1.
b1000 #
b1000 '
b1000 %
#1850000
0+
b1100 !
b1100 /
1)
1(
b1001 #
b1001 '
b1001 %
#1860000
1+
1*
0,
b10 !
b10 /
0(
b1010 #
b1010 '
b1010 %
#1870000
0+
b1001 !
b1001 /
0)
1(
b1011 #
b1011 '
b1011 %
#1880000
0+
1,
b1101 !
b1101 /
1*
1-
0(
b1100 #
b1100 '
b1100 %
#1890000
1+
b110 !
b110 /
1)
1(
b1101 #
b1101 '
b1101 %
#1900000
0+
0*
0,
b1000 !
b1000 /
0(
b1110 #
b1110 '
b1110 %
#1910000
1+
b11 !
b11 /
0)
1(
b1111 #
b1111 '
b1111 %
#1920000
0-
b0 !
b0 /
0*
0+
0,
0.
0(
b0 #
b0 '
b1100 "
b1100 &
b1100 $
b0 %
#1930000
b1100 !
b1100 /
1+
1*
b1 #
b1 '
b1 %
#1940000
b1011 !
b1011 /
0*
1,
b10 #
b10 '
b10 %
#1950000
b111 !
b111 /
0+
1*
b11 #
b11 '
b11 %
#1960000
0*
b101 !
b101 /
1-
b100 #
b100 '
b100 %
#1970000
b1001 !
b1001 /
1+
1*
b101 #
b101 '
b101 %
#1980000
b1110 !
b1110 /
0*
0,
b110 #
b110 '
b110 %
#1990000
b10 !
b10 /
0+
1*
b111 #
b111 '
b111 %
#2000000
0*
b1010 !
b1010 /
1.
b1000 #
b1000 '
b1000 %
#2010000
b110 !
b110 /
1+
1*
b1001 #
b1001 '
b1001 %
#2020000
b1 !
b1 /
0*
1,
b1010 #
b1010 '
b1010 %
#2030000
b1101 !
b1101 /
0+
1*
b1011 #
b1011 '
b1011 %
#2040000
0*
b1111 !
b1111 /
0-
b1100 #
b1100 '
b1100 %
#2050000
b11 !
b11 /
1+
1*
b1101 #
b1101 '
b1101 %
#2060000
b100 !
b100 /
0*
0,
b1110 #
b1110 '
b1110 %
#2070000
b1000 !
b1000 /
0+
1*
b1111 #
b1111 '
b1111 %
#2080000
0*
b0 !
b0 /
0.
b0 #
b0 '
b1101 "
b1101 &
b1101 $
b0 %
#2090000
1+
1*
b1101 !
b1101 /
1(
b1 #
b1 '
b1 %
#2100000
0*
1,
b1001 !
b1001 /
1)
0(
b10 #
b10 '
b10 %
#2110000
0+
1*
b100 !
b100 /
1(
b11 #
b11 '
b11 %
#2120000
b1 !
b1 /
0)
1*
1-
0(
b100 #
b100 '
b100 %
#2130000
1+
0*
b1100 !
b1100 /
1(
b101 #
b101 '
b101 %
#2140000
1*
0,
b1000 !
b1000 /
1)
0(
b110 #
b110 '
b110 %
#2150000
0+
0*
b101 !
b101 /
1(
b111 #
b111 '
b111 %
#2160000
0)
0*
1+
b10 !
b10 /
0(
1.
b1000 #
b1000 '
b1000 %
#2170000
0+
1*
b1111 !
b1111 /
1(
b1001 #
b1001 '
b1001 %
#2180000
0*
1,
b1011 !
b1011 /
1)
0(
b1010 #
b1010 '
b1010 %
#2190000
1+
1*
b110 !
b110 /
1(
b1011 #
b1011 '
b1011 %
#2200000
b11 !
b11 /
0)
1*
0-
0(
b1100 #
b1100 '
b1100 %
#2210000
0+
0*
b1110 !
b1110 /
1(
b1101 #
b1101 '
b1101 %
#2220000
1*
0,
b1010 !
b1010 /
1)
0(
b1110 #
b1110 '
b1110 %
#2230000
1+
0*
b111 !
b111 /
1(
b1111 #
b1111 '
b1111 %
#2240000
b0 !
b0 /
0)
0*
0+
0.
0(
b0 #
b0 '
b1110 "
b1110 &
b1110 $
b0 %
#2250000
b1110 !
b1110 /
1+
1*
1)
b1 #
b1 '
b1 %
#2260000
b1111 !
b1111 /
1,
0)
b10 #
b10 '
b10 %
#2270000
b1 !
b1 /
0+
0*
1)
b11 #
b11 '
b11 %
#2280000
1+
b1101 !
b1101 /
0)
1-
b100 #
b100 '
b100 %
#2290000
b11 !
b11 /
0+
1*
1)
b101 #
b101 '
b101 %
#2300000
b10 !
b10 /
0,
0)
b110 #
b110 '
b110 %
#2310000
b1100 !
b1100 /
1+
0*
1)
b111 #
b111 '
b111 %
#2320000
0+
0)
1,
b1001 !
b1001 /
1.
b1000 #
b1000 '
b1000 %
#2330000
b111 !
b111 /
1+
1*
1)
b1001 #
b1001 '
b1001 %
#2340000
b110 !
b110 /
0,
0)
b1010 #
b1010 '
b1010 %
#2350000
b1000 !
b1000 /
0+
0*
1)
b1011 #
b1011 '
b1011 %
#2360000
1+
b100 !
b100 /
0)
0-
b1100 #
b1100 '
b1100 %
#2370000
b1010 !
b1010 /
0+
1*
1)
b1101 #
b1101 '
b1101 %
#2380000
b1011 !
b1011 /
1,
0)
b1110 #
b1110 '
b1110 %
#2390000
b101 !
b101 /
1+
0*
1)
b1111 #
b1111 '
b1111 %
#2400000
0+
0)
0,
b0 !
b0 /
0.
b0 #
b0 '
b1111 "
b1111 &
b1111 $
b0 %
#2410000
1+
1*
b1111 !
b1111 /
1)
1(
b1 #
b1 '
b1 %
#2420000
1,
b1101 !
b1101 /
0(
b10 #
b10 '
b10 %
#2430000
0+
0*
b10 !
b10 /
0)
1(
b11 #
b11 '
b11 %
#2440000
1+
b1001 !
b1001 /
1*
1-
0(
b100 #
b100 '
b100 %
#2450000
0+
0*
b110 !
b110 /
1)
1(
b101 #
b101 '
b101 %
#2460000
0,
b100 !
b100 /
0(
b110 #
b110 '
b110 %
#2470000
1+
1*
b1011 !
b1011 /
0)
1(
b111 #
b111 '
b111 %
#2480000
0*
1+
1,
b1 !
b1 /
0(
1.
b1000 #
b1000 '
b1000 %
#2490000
0+
1*
b1110 !
b1110 /
1)
1(
b1001 #
b1001 '
b1001 %
#2500000
0,
b1100 !
b1100 /
0(
b1010 #
b1010 '
b1010 %
#2510000
1+
0*
b11 !
b11 /
0)
1(
b1011 #
b1011 '
b1011 %
#2520000
0+
b1000 !
b1000 /
1*
0-
0(
b1100 #
b1100 '
b1100 %
#2530000
1+
0*
b111 !
b111 /
1)
1(
b1101 #
b1101 '
b1101 %
#2540000
1,
b101 !
b101 /
0(
b1110 #
b1110 '
b1110 %
#2550000
0+
1*
b1010 !
b1010 /
0)
1(
b1111 #
b1111 '
b1111 %
#2560000
b10000 $
b10000 %
